{
  "version": "0.11.2",
  "uuid": "748a6327-3ec4-4b41-af70-e036738dabf1",
  "root": "/github/workspace",
  "codebase": {
    "totals": {
      "TypeScript": {
        "files": 4,
        "lines_of_code": 288,
        "functions": 20,
        "hard_to_maintain": 2,
        "unmaintainable": 0
      }
    },
    "tree": {
      "./": {
        "entries": [
          "src/"
        ],
        "profile": [118, 47, 88, 0]
      },
      "src/": {
        "entries": [
          "action.ts",
          "codelimit.ts",
          "utils.ts",
          "github.ts"
        ],
        "profile": [118, 47, 88, 0]
      }
    },
    "files": {
      "src/action.ts": {
        "checksum": "b01b7029556af689ae8b86f5e5e67323",
        "language": "TypeScript",
        "loc": 83,
        "profile": [11, 0, 55, 0],
        "measurements": [
          {"unit_name": "generateMarkdownReport", "start": {"line": 18, "column": 16}, "end": {"line": 28, "column": 2}, "value": 11},
          {"unit_name": "main", "start": {"line": 30, "column": 16}, "end": {"line": 84, "column": 2}, "value": 55}
        ]
      },
      "src/codelimit.ts": {
        "checksum": "9f398dd35c5170e2adbbb6ddd33cfdea",
        "language": "TypeScript",
        "loc": 65,
        "profile": [42, 17, 0, 0],
        "measurements": [
          {"unit_name": "getBinaryName", "start": {"line": 9, "column": 10}, "end": {"line": 25, "column": 2}, "value": 17},
          {"unit_name": "getLatestBinaryUrl", "start": {"line": 27, "column": 16}, "end": {"line": 32, "column": 2}, "value": 6},
          {"unit_name": "downloadCodeLimitBinary", "start": {"line": 34, "column": 23}, "end": {"line": 43, "column": 2}, "value": 10},
          {"unit_name": "getReportContent", "start": {"line": 45, "column": 17}, "end": {"line": 47, "column": 2}, "value": 3},
          {"unit_name": "makeBadgeSvg", "start": {"line": 49, "column": 10}, "end": {"line": 56, "column": 2}, "value": 8},
          {"unit_name": "getBadgeContent", "start": {"line": 58, "column": 17}, "end": {"line": 72, "column": 2}, "value": 15}
        ]
      },
      "src/utils.ts": {
        "checksum": "87a66705537fb7d7ef83bd49e71ea687",
        "language": "TypeScript",
        "loc": 35,
        "profile": [0, 0, 33, 0],
        "measurements": [
          {"unit_name": "getChangedFiles", "start": {"line": 4, "column": 23}, "end": {"line": 36, "column": 2}, "value": 33}
        ]
      },
      "src/github.ts": {
        "checksum": "02f8382906cc5766350ecc9cf15e890c",
        "language": "TypeScript",
        "loc": 105,
        "profile": [65, 30, 0, 0],
        "measurements": [
          {"unit_name": "branchExists", "start": {"line": 5, "column": 23}, "end": {"line": 14, "column": 2}, "value": 10},
          {"unit_name": "createBranch", "start": {"line": 16, "column": 23}, "end": {"line": 26, "column": 2}, "value": 11},
          {"unit_name": "createInitialCommit", "start": {"line": 28, "column": 23}, "end": {"line": 38, "column": 2}, "value": 11},
          {"unit_name": "getRepoOwner", "start": {"line": 40, "column": 17}, "end": {"line": 42, "column": 2}, "value": 3},
          {"unit_name": "getRepoName", "start": {"line": 44, "column": 17}, "end": {"line": 46, "column": 2}, "value": 3},
          {"unit_name": "getIdentity", "start": {"line": 48, "column": 23}, "end": {"line": 48, "column": 93}, "value": 1},
          {"unit_name": "createOrUpdateFile", "start": {"line": 63, "column": 23}, "end": {"line": 93, "column": 2}, "value": 30},
          {"unit_name": "createPRComment", "start": {"line": 95, "column": 23}, "end": {"line": 102, "column": 2}, "value": 8},
          {"unit_name": "isPullRequest", "start": {"line": 104, "column": 17}, "end": {"line": 106, "column": 2}, "value": 3},
          {"unit_name": "getSourceBranch", "start": {"line": 108, "column": 17}, "end": {"line": 114, "column": 2}, "value": 7},
          {"unit_name": "createBranchIfNotExists", "start": {"line": 116, "column": 23}, "end": {"line": 123, "column": 2}, "value": 8}
        ]
      }
    }
  }
}
